collective.pdbpp-1.0.0a8-py3.12-nspkg.pth
collective/pdbpp/__init__.py
collective/pdbpp/configure.zcml
collective_pdbpp-1.0.0a8.dist-info/licenses/LICENSE.GPL
collective_pdbpp-1.0.0a8.dist-info/licenses/LICENSE.md
collective_pdbpp-1.0.0a8.dist-info/METADATA
collective_pdbpp-1.0.0a8.dist-info/WHEEL
collective_pdbpp-1.0.0a8.dist-info/entry_points.txt
collective_pdbpp-1.0.0a8.dist-info/namespace_packages.txt
collective_pdbpp-1.0.0a8.dist-info/top_level.txt
collective_pdbpp-1.0.0a8.dist-info/RECORD
